Workbook

Sheet Project Data
A1: Invoice No. | B1: Client Name | C1: Project Type | D1: Assigned To | E1: Invoice Date | F1: Work Date | G1: Bill Amount (INR) | H1: Actual Cost (INR) | I1: Profit (INR) | J1: Profit % | K1: Month | L1: Status
A2: 1 | B2: Apurv | C2: Engagement Shoot | D2: Abhishek Anjan | E2: 14-Jan-2025 | F2: 02-Feb-2025 | G2: 25000 | H2: 22000 | I2: 3000 | J2: =I2/G2 -> 0.12 | K2: Jan | L2: Completed
A3: 2 | B3: Pankaj Upadhyay | C3: Traditional Wedding | D3: Alex Soy | E3: 21-Jan-2025 | F3: 17-Feb-2025 | G3: 30000 | H3: 26700 | I3: 3300 | J3: =I3/G3 -> 0.11 | K3: Jan | L3: Completed
A4: 3 | B4: Shivanand | C4: Cinematic Wedding | D4: Sanjeet | E4: 22-Jan-2025 | F4: 30-Apr-2025 | G4: 65000 | H4: 56550 | I4: 8450 | J4: =I4/G4 -> 0.13 | K4: Jan | L4: Completed
A5: 4 | B5: Manish Anand | C5: Traditional Wedding | D5: Abhishek Anjan | E5: 13-Feb-2025 | F5: 08-Mar-2025 | G5: 35000 | H5: 31500 | I5: 3500 | J5: =I5/G5 -> 0.1 | K5: Feb | L5: Completed
A6: 5 | B6: Ankita Raj | C6: Cinematic Engagement | D6: Alex Soy | E6: 02-Mar-2025 | F6: 07-Mar-2025 | G6: 17000 | H6: 14960 | I6: 2040 | J6: =I6/G6 -> 0.12 | K6: Mar | L6: Completed
A7: 6 | B7: Apurv | C7: Cinematic Wedding | D7: Sanjeet | E7: 14-Apr-2025 | F7: 25-May-2025 | G7: 87000 | H7: 74820 | I7: 12180 | J7: =I7/G7 -> 0.14 | K7: Apr | L7: Completed
A8: 7 | B8: Apurv | C8: Haldi Shoot | D8: Abhishek Anjan | E8: 01-May-2025 | F8: 04-Jun-2025 | G8: 9000 | H8: 8100 | I8: 900 | J8: =I8/G8 -> 0.1 | K8: May | L8: Completed
A9: 8 | B9: Arsalan | C9: Traditional Wedding | D9: Alex Soy | E9: 03-Aug-2025 | F9: 10-Aug-2025 | G9: 40000 | H9: 35600 | I9: 4400 | J9: =I9/G9 -> 0.11 | K9: Aug | L9: Completed
A10: 9 | B10: Vicky Nayak | C10: Cinematic Wedding | D10: Sanjeet | E10: 24-Aug-2025 | F10: 27-Feb-2026 | G10: 90000 | H10: 78300 | I10: 11700 | J10: =I10/G10 -> 0.13 | K10: Aug | L10: Completed
A11: 10 | B11: Sunita Devi | C11: Cinematic Wedding | D11: Abhishek Anjan | E11: 13-Sep-2025 | F11: 29-Nov-2025 | G11: 60000 | H11: 52800 | I11: 7200 | J11: =I11/G11 -> 0.12 | K11: Sep | L11: Completed
A12: 11 | B12: Aditya Jha | C12: Cinematic Wedding | D12: Alex Soy | E12: 15-Oct-2025 | F12: 24-Oct-2025 | G12: 5000 | H12: 4500 | I12: 500 | J12: =I12/G12 -> 0.1 | K12: Oct | L12: Completed
A13: 12 | B13: Nishant Singh | C13: Cinematic Wedding | D13: Sanjeet | E13: 21-Oct-2025 | F13: 06-Dec-2025 | G13: 145000 | H13: 123250 | I13: 21750 | J13: =I13/G13 -> 0.15 | K13: Oct | L13: Completed
... A15: 14 | B15: Raj Kishore Singh | C15: Cinematic Wedding | D15: Alex Soy | E15: 08-Dec-2025 | F15: 23-Feb-2026 | G15: 120000 | H15: 103200 | I15: 16800 | J15: =I15/G15 -> 0.14 | K15: Dec | L15: Completed

Sheet KPI Dashboard
A1: THE TIMELESS PICTURES — OPERATIONS DASHBOARD 2025
A2: Photography Business | Jamshedpur, India | Jan 2025 – Dec 2025 | 14 Real Client Projects
A4: TOTAL PROJECTS | E4: TOTAL BILLED (INR) | I4: TOTAL PROFIT (INR) | M4: AVG PROFIT MARGIN
A5: =COUNTA('Project Data'!A2:A15) -> 14 | E5: =SUM('Project Data'!G2:G15) -> 753000 | I5: =SUM('Project Data'!I2:I15) -> 98720 | M5: =SUM('Project Data'!I2:I15)/SUM('Project Data'!G2:G15) -> 0.13110226
A7: Jan – Dec 2025 | E7: Jan – Dec 2025 | I7: Jan – Dec 2025 | M7: Jan – Dec 2025
A9: TOTAL ACTUAL COST | E9: HIGHEST SINGLE PROJECT | I9: AVG PROJECT VALUE | M9: COMPLETED PROJECTS
A10: =SUM('Project Data'!H2:H15) -> 654280 | E10: =MAX('Project Data'!G2:G15) -> 145000 | I10: =AVERAGE('Project Data'!G2:G15) -> 53785.714 | M10: =COUNTIF('Project Data'!L2:L15,"Completed") -> 14
A12: Jan – Dec 2025 | E12: Jan – Dec 2025 | I12: Jan – Dec 2025 | M12: Jan – Dec 2025

Sheet Monthly Analysis
A1: MONTHLY REVENUE & COST ANALYSIS — The Timeless Pictures 2025
A3: Month | B3: Projects | C3: Billed (INR) | D3: Cost (INR) | E3: Profit (INR) | F3: Profit Margin %
A4: Jan | B4: 3 | C4: 120000 | D4: 105250 | E4: =C4-D4 -> 14750 | F4: =IF(C4>0,E4/C4,0) -> 0.12291667
A5: Feb | B5: 1 | C5: 35000 | D5: 31500 | E5: =C5-D5 -> 3500 | F5: =IF(C5>0,E5/C5,0) -> 0.1
A6: Mar | B6: 1 | C6: 17000 | D6: 14960 | E6: =C6-D6 -> 2040 | F6: =IF(C6>0,E6/C6,0) -> 0.12
A7: Apr | B7: 1 | C7: 87000 | D7: 74820 | E7: =C7-D7 -> 12180 | F7: =IF(C7>0,E7/C7,0) -> 0.14
A8: May | B8: 1 | C8: 9000 | D8: 8100 | E8: =C8-D8 -> 900 | F8: =IF(C8>0,E8/C8,0) -> 0.1
A9: Jun | B9: - | C9: - | D9: - | E9: 0 | F9: 0
A10: Jul | B10: - | C10: - | D10: - | E10: 0 | F10: 0
A11: Aug | B11: 2 | C11: 130000 | D11: 113900 | E11: =C11-D11 -> 16100 | F11: =IF(C11>0,E11/C11,0) -> 0.12384615
A12: Sep | B12: 1 | C12: 60000 | D12: 52800 | E12: =C12-D12 -> 7200 | F12: =IF(C12>0,E12/C12,0) -> 0.12
A13: Oct | B13: 2 | C13: 150000 | D13: 127750 | E13: =C13-D13 -> 22250 | F13: =IF(C13>0,E13/C13,0) -> 0.14833333
A14: Nov | B14: 1 | C14: 25000 | D14: 22000 | E14: =C14-D14 -> 3000 | F14: =IF(C14>0,E14/C14,0) -> 0.12
A15: Dec | B15: 1 | C15: 120000 | D15: 103200 | E15: =C15-D15 -> 16800 | F15: =IF(C15>0,E15/C15,0) -> 0.14
A16: TOTAL | B16: =SUM(B4:B15) -> 14 | C16: =SUM(C4:C15) -> 753000 | D16: =SUM(D4:D15) -> 654280 | E16: =SUM(E4:E15) -> 98720 | F16: =E16/C16 -> 0.13110226

Sheet Team Performance
A1: TEAM PERFORMANCE TRACKER — The Timeless Pictures 2025
A3: Team Member | B3: Role | C3: Projects | D3: Total Billed (INR) | E3: Total Cost (INR) | F3: Total Profit (INR) | G3: Avg Profit Margin
A4: Abhishek Anjan | B4: Operations Lead | C4: =COUNTIF('Project Data'!D:D,A4) -> 5 | D4: =SUMIF('Project Data'!D:D,A4,'Project Data'!G:G) -> 154000 | E4: =SUMIF('Project Data'!D:D,A4,'Project Data'!H:H) -> 136400 | F4: =SUMIF('Project Data'!D:D,A4,'Project Data'!I:I) -> 17600 | G4: =IF(D4>0,F4/D4,0) -> 0.11428571
A5: Alex Soy | B5: Photographer / Videographer | C5: =COUNTIF('Project Data'!D:D,A5) -> 5 | D5: =SUMIF('Project Data'!D:D,A5,'Project Data'!G:G) -> 212000 | E5: =SUMIF('Project Data'!D:D,A5,'Project Data'!H:H) -> 184960 | F5: =SUMIF('Project Data'!D:D,A5,'Project Data'!I:I) -> 27040 | G5: =IF(D5>0,F5/D5,0) -> 0.12754717
A6: Sanjeet | B6: Photographer / Cinematographer | C6: =COUNTIF('Project Data'!D:D,A6) -> 4 | D6: =SUMIF('Project Data'!D:D,A6,'Project Data'!G:G) -> 387000 | E6: =SUMIF('Project Data'!D:D,A6,'Project Data'!H:H) -> 332920 | F6: =SUMIF('Project Data'!D:D,A6,'Project Data'!I:I) -> 54080 | G6: =IF(D6>0,F6/D6,0) -> 0.1397416
A7: TOTAL | B7: — | C7: =SUM(C4:C6) -> 14 | D7: =SUM(D4:D6) -> 753000 | E7: =SUM(E4:E6) -> 654280 | F7: =SUM(F4:F6) -> 98720 | G7: =F7/D7 -> 0.13110226
A9: KEY INSIGHTS
A10: • Total revenue billed across all 14 projects: ₹753,000 with an average profit margin of 13.1%.
A11: • Sanjeet managed the highest-value projects totalling ₹387,000 — driven by Cinematic Wedding bookings.
A12: • Nishant Singh (₹1,45,000) and Raj Kishore Singh (₹1,20,000) are the two highest-value clients — priority retention targets.
A13: • Cinematic Wedding is the highest-revenue project type — strategic focus for premium pricing and upsells.
A14: • All 14 projects marked Completed — 100% delivery rate maintained across the 2025 booking calendar.

Sheet Project Type Analysis
A1: PROJECT TYPE REVENUE BREAKDOWN — The Timeless Pictures 2025
A3: Project Type | B3: No. of Projects | C3: Total Billed (INR) | D3: Total Cost (INR) | E3: Total Profit (INR) | F3: Avg Profit Margin
A4: Cinematic Wedding | B4: 7 | C4: 572000 | D4: 493420 | E4: 78580 | F4: =E4/C4 -> 0.13737762
A5: Traditional Wedding | B5: 3 | C5: 105000 | D5: 93800 | E5: 11200 | F5: =E5/C5 -> 0.10666667
A6: Cinematic Engagement | B6: 2 | C6: 42000 | D6: 36960 | E6: 5040 | F6: =E6/C6 -> 0.12
A7: Engagement Shoot | B7: 1 | C7: 25000 | D7: 22000 | E7: 3000 | F7: =E7/C7 -> 0.12
A8: Haldi Shoot | B8: 1 | C8: 9000 | D8: 8100 | E8: 900 | F8: =E8/C8 -> 0.1
A9: TOTAL | B9: =SUM(B4:B8) -> 14 | C9: =SUM(C4:C8) -> 753000 | D9: =SUM(D4:D8) -> 654280 | E9: =SUM(E4:E8) -> 98720 | F9: =E9/C9 -> 0.13110226
